apkInspector/__init__.py
apkInspector/axml.py
apkInspector/extract.py
apkInspector/headers.py
apkInspector/helpers.py
apkInspector/indicators.py
apkInspectorCLI/__init__.py
apkInspectorCLI/main.py
apkinspector-1.3.3.dist-info/LICENSE
apkinspector-1.3.3.dist-info/METADATA
apkinspector-1.3.3.dist-info/WHEEL
apkinspector-1.3.3.dist-info/entry_points.txt
apkinspector-1.3.3.dist-info/RECORD
