Metadata-Version: 2.3
Name: apkInspector
Version: 1.3.3
Summary: apkInspector is a tool designed to provide detailed insights into the zip structure of APK files, offering the capability to extract content and decode the AndroidManifest.xml file.
License: Apache-2.0
Author: erev0s
Author-email: projects@erev0s.com
Requires-Python: >=3.5,<4.0
Classifier: License :: OSI Approved :: Apache Software License
Classifier: Programming Language :: Python :: 3
Classifier: Programming Language :: Python :: 3.5
Classifier: Programming Language :: Python :: 3.6
Classifier: Programming Language :: Python :: 3.7
Classifier: Programming Language :: Python :: 3.8
Classifier: Programming Language :: Python :: 3.9
Classifier: Programming Language :: Python :: 3.10
Classifier: Programming Language :: Python :: 3.11
Classifier: Programming Language :: Python :: 3.12
Classifier: Programming Language :: Python :: 3.13
Project-URL: Repository, https://github.com/erev0s/apkInspector
